CHANGES.md
MANIFEST.in
README.md
pytest.ini
setup.cfg
setup.py
tox.ini
elixr/__init__.py
elixr.base.egg-info/PKG-INFO
elixr.base.egg-info/SOURCES.txt
elixr.base.egg-info/dependency_links.txt
elixr.base.egg-info/not-zip-safe
elixr.base.egg-info/requires.txt
elixr.base.egg-info/top_level.txt
elixr/base/__init__.py
elixr/base/_compat.py
elixr/base/cli.py
elixr/base/threadlocal.py