Metadata-Version: 1.0
Name: elixr.base
Version: 0.3
Summary: A python general purpose utility library
Home-page: https://github.com/babdulhakim2/elixr.base.git
Author: Abdul-Hakeem Shaibu
Author-email: hkmshb@gmail.com
License: UNKNOWN
Keywords: elixr.base,hazeltek elixr.base
Platform: any
